LICENSE
README.md
ml_methods/__init__.py
ml_methods/algoutils.py
ml_methods/gda.py
ml_methods/linreg.py
ml_methods/linsys.py
ml_methods/logreg.py
ml_methods/solnfn.py
ml_methods-0.2.1.dist-info/METADATA
ml_methods-0.2.1.dist-info/WHEEL
ml_methods-0.2.1.dist-info/licenses/LICENSE
ml_methods-0.2.1.dist-info/RECORD
